{"config_list": "[{\"op_types\": [\"Conv2d\"], \"op_names\": [\"layer2.2.conv2\"], \"sparsity\": 8.437942647390027e-06}, {\"op_types\": [\"Conv2d\"], \"op_names\": [\"layer2.3.conv2\"], \"sparsity\": 0.0003136017296373435}, {\"op_types\": [\"Conv2d\"], \"op_names\": [\"layer3.0.conv3\"], \"sparsity\": 0.010426611312363608}, {\"op_types\": [\"Conv2d\"], \"op_names\": [\"layer3.1.conv1\"], \"sparsity\": 0.012034829809419622}, {\"op_types\": [\"Conv2d\"], \"op_names\": [\"layer3.1.conv3\"], \"sparsity\": 0.014102551696584698}, {\"op_types\": [\"Conv2d\"], \"op_names\": [\"layer3.2.conv1\"], \"sparsity\": 0.02188476241885743}, {\"op_types\": [\"Conv2d\"], \"op_names\": [\"layer3.2.conv3\"], \"sparsity\": 0.026392276710824475}, {\"op_types\": [\"Conv2d\"], \"op_names\": [\"layer3.3.conv1\"], \"sparsity\": 0.03018516711587082}, {\"op_types\": [\"Conv2d\"], \"op_names\": [\"layer3.3.conv3\"], \"sparsity\": 0.03404414207164565}, {\"op_types\": [\"Conv2d\"], \"op_names\": [\"layer3.4.conv1\"], \"sparsity\": 0.03829043572070358}, {\"op_types\": [\"Conv2d\"], \"op_names\": [\"layer3.4.conv3\"], \"sparsity\": 0.04701640880763298}, {\"op_types\": [\"Conv2d\"], \"op_names\": [\"layer3.5.conv1\"], \"sparsity\": 0.0511895137740293}, {\"op_types\": [\"Conv2d\"], \"op_names\": [\"layer3.5.conv3\"], \"sparsity\": 0.05274458809030634}, {\"op_types\": [\"Conv2d\"], \"op_names\": [\"layer3.0.shortcut.0\"], \"sparsity\": 0.06501993040055752}, {\"op_types\": [\"Conv2d\"], \"op_names\": [\"layer4.0.conv1\"], \"sparsity\": 0.066634512058293}, {\"op_types\": [\"Conv2d\"], \"op_names\": [\"layer3.0.conv2\"], \"sparsity\": 0.06733837791666528}, {\"op_types\": [\"Conv2d\"], \"op_names\": [\"layer3.1.conv2\"], \"sparsity\": 0.06737090549758691}, {\"op_types\": [\"Conv2d\"], \"op_names\": [\"layer3.2.conv2\"], \"sparsity\": 0.08238956170019943}, {\"op_types\": [\"Conv2d\"], \"op_names\": [\"layer3.3.conv2\"], \"sparsity\": 0.08591807422175848}, {\"op_types\": [\"Conv2d\"], \"op_names\": [\"layer3.4.conv2\"], \"sparsity\": 0.09695172812690055}, {\"op_types\": [\"Conv2d\"], \"op_names\": [\"layer3.5.conv2\"], \"sparsity\": 0.0974032269882595}, {\"op_types\": [\"Conv2d\"], \"op_names\": [\"layer4.0.conv3\"], \"sparsity\": 0.1039160479189975}, {\"op_types\": [\"Conv2d\"], \"op_names\": [\"layer4.1.conv1\"], \"sparsity\": 0.10580022672055919}, {\"op_types\": [\"Conv2d\"], \"op_names\": [\"layer4.1.conv3\"], \"sparsity\": 0.10782992418469943}, {\"op_types\": [\"Conv2d\"], \"op_names\": [\"layer4.2.conv1\"], \"sparsity\": 0.11539178241860197}, {\"op_types\": [\"Conv2d\"], \"op_names\": [\"layer4.2.conv3\"], \"sparsity\": 0.12376118001138971}, {\"op_types\": [\"Conv2d\"], \"op_names\": [\"layer4.0.shortcut.0\"], \"sparsity\": 0.1313590206025819}, {\"op_types\": [\"Conv2d\"], \"op_names\": [\"layer4.0.conv2\"], \"sparsity\": 0.1362895407940817}, {\"op_types\": [\"Conv2d\"], \"op_names\": [\"layer4.1.conv2\"], \"sparsity\": 0.14036037363662568}, {\"op_types\": [\"Conv2d\"], \"op_names\": [\"layer4.2.conv2\"], \"sparsity\": 0.16178118236068376}]", "performance": 0.9495}